LICENSE.txt
MANIFEST.in
README.md
setup.cfg
setup.py
quillbot/__init__.py
quillbot/cli.py
quillbot/settings.py
quillbot/utils.py
quillbot/api/__init__.py
quillbot/api/appbuilder.py
quillbot/api/main.py
quillbot/api/middleware.py
quillbot/api/router.py
quillbot/api/resources/__init__.py
quillbot/api/resources/paraphrasing.py
quillbot/quillbot_selenium/__init__.py
quillbot/quillbot_selenium/common.py
quillbot/quillbot_selenium/quillbot_paths.py
quillbot/quillbot_selenium/quillbot_scripts.py
quillbot_cat.egg-info/PKG-INFO
quillbot_cat.egg-info/SOURCES.txt
quillbot_cat.egg-info/dependency_links.txt
quillbot_cat.egg-info/entry_points.txt
quillbot_cat.egg-info/requires.txt
quillbot_cat.egg-info/top_level.txt
quillbot_cat.egg-info/zip-safe
tests/__init__.py
tests/api/__init__.py
tests/api/base.py
tests/api/resources/__init__.py
tests/api/resources/test_paraphrasing.py
tests/quillbot_selenium/__init__.py
tests/quillbot_selenium/test_quillbot.py