Metadata-Version: 2.1
Name: quillbot-cat
Version: 0.0.1
Summary: TWNTY Quillbot API
Home-page: UNKNOWN
Author: Kristina Kurhanska
Author-email: kurganska@twnty.de
License: UNKNOWN
Platform: UNKNOWN
License-File: LICENSE.txt
